atypes/__init__.py
atypes/scrap/__init__.py
atypes/scrap/qc.py
atypes/scrap/slang.py
atypes-0.0.2.dist-info/LICENSE
atypes-0.0.2.dist-info/METADATA
atypes-0.0.2.dist-info/WHEEL
atypes-0.0.2.dist-info/top_level.txt
atypes-0.0.2.dist-info/RECORD
