Metadata-Version: 2.1
Name: atypes
Version: 0.0.2
Summary: Abstractions for signal machine learning.
Home-page: https://github.com/otosense/atypes
Author: OtoSense
License: apache-2.0
Platform: any
